GIANDB/__init__.py
GIANDB/congia/__init__.py
GIANDB/congia/autogianap.py
ESPEROOK-0.0.2.dist-info/LICENSE
ESPEROOK-0.0.2.dist-info/METADATA
ESPEROOK-0.0.2.dist-info/WHEEL
ESPEROOK-0.0.2.dist-info/entry_points.txt
ESPEROOK-0.0.2.dist-info/top_level.txt
ESPEROOK-0.0.2.dist-info/RECORD
